spb_dnevnik_bot/__about__.py
spb_dnevnik_bot/__init__.py
spb_dnevnik_bot/bot.py
spb_dnevnik_bot/main.py
spb_dnevnik_bot/message_handlers.py
spb_dnevnik_bot/parser.py
spb_dnevnik_bot/lib/phantomjs
spb_dnevnik_bot-0.2.0.dist-info/LICENSE
spb_dnevnik_bot-0.2.0.dist-info/METADATA
spb_dnevnik_bot-0.2.0.dist-info/WHEEL
spb_dnevnik_bot-0.2.0.dist-info/entry_points.txt
spb_dnevnik_bot-0.2.0.dist-info/top_level.txt
spb_dnevnik_bot-0.2.0.dist-info/RECORD
