Metadata-Version: 2.1
Name: spb-dnevnik-bot
Version: 0.2.0
Summary: Telegram bot for school journal at petersburgedu.ru
Home-page: https://github.com/bargool/spb-dnevnik-bot
Author: Aleksey Nakoryakov
Author-email: bargool@gmail.com
License: MIT
Platform: UNKNOWN
Classifier: License :: OSI Approved :: MIT License
Classifier: Programming Language :: Python
Classifier: Programming Language :: Python :: 3.6
Classifier: Programming Language :: Python :: 3.7
Classifier: Programming Language :: Python :: Implementation :: CPython
Classifier: Programming Language :: Python :: Implementation :: PyPy
Requires-Dist: requests
Requires-Dist: pytils
Requires-Dist: lxml
Requires-Dist: selenium
Requires-Dist: dateparser
Requires-Dist: python-telegram-bot
